dida/__init__.py
dida/client.py
dida/exceptions.py
dida/api/__init__.py
dida/api/base.py
dida/api/project.py
dida/api/tag.py
dida/api/tasks.py
dida/models/__init__.py
dida/models/base.py
dida/models/project.py
dida/models/tag.py
dida/models/task.py
dida/tests/__init__.py
dida/utils/__init__.py
dida/utils/auth.py
dida/utils/http.py
didatodolist-1.0.0.dist-info/LICENSE
didatodolist-1.0.0.dist-info/METADATA
didatodolist-1.0.0.dist-info/WHEEL
didatodolist-1.0.0.dist-info/top_level.txt
didatodolist-1.0.0.dist-info/RECORD
