Metadata-Version: 2.1
Name: didatodolist
Version: 1.0.0
Summary: 滴答清单(TickTick/Dida365) Python SDK
Home-page: https://github.com/GalaxyXieyu/dida_api
Author: xieyu
Author-email: 523018705@qq.com
Keywords: dida365 ticktick todo task management api sdk
Classifier: Development Status :: 4 - Beta
Classifier: Intended Audience :: Developers
Classifier: License :: OSI Approved :: MIT License
Classifier: Operating System :: OS Independent
Classifier: Programming Language :: Python :: 3
Classifier: Programming Language :: Python :: 3.7
Classifier: Programming Language :: Python :: 3.8
Classifier: Programming Language :: Python :: 3.9
Classifier: Programming Language :: Python :: 3.10
Classifier: Programming Language :: Python :: 3.11
Classifier: Topic :: Software Development :: Libraries :: Python Modules
Requires-Python: >=3.7
License-File: LICENSE
Requires-Dist: requests >=2.25.0
Requires-Dist: python-dateutil >=2.8.0
Requires-Dist: pytz >=2024.1
